ape_safe/__init__.py
ape_safe/accounts.py
ape_safe/cli.py
ape_safe/config.py
ape_safe/exceptions.py
ape_safe/factory.py
ape_safe/modules.py
ape_safe/multisend.py
ape_safe/packages.py
ape_safe/types.py
ape_safe/utils.py
ape_safe/version.py
ape_safe/_cli/__init__.py
ape_safe/_cli/click_ext.py
ape_safe/_cli/delegates.py
ape_safe/_cli/modules.py
ape_safe/_cli/pending.py
ape_safe/_cli/safe_mgmt.py
ape_safe/client/__init__.py
ape_safe/client/base.py
ape_safe/client/mock.py
ape_safe/client/types.py
ape_safe/manifests/safe-v1.3.0.json
ape_safe/manifests/safe-v1.4.1.json
ape_safe-0.8.23.dist-info/licenses/LICENSE
ape_safe-0.8.23.dist-info/METADATA
ape_safe-0.8.23.dist-info/WHEEL
ape_safe-0.8.23.dist-info/entry_points.txt
ape_safe-0.8.23.dist-info/top_level.txt
ape_safe-0.8.23.dist-info/RECORD
