Metadata-Version: 2.4
Name: ape-safe
Version: 0.8.23
Summary: ape-safe: Gnosis Safe account plugin for Ape
Home-page: https://github.com/ApeWorX/ape-safe
Author: ApeWorX Ltd.
Author-email: admin@apeworx.io
License: Apache-2.0
Keywords: ethereum
Classifier: Development Status :: 5 - Production/Stable
Classifier: Intended Audience :: Developers
Classifier: License :: OSI Approved :: Apache Software License
Classifier: Natural Language :: English
Classifier: Operating System :: MacOS
Classifier: Operating System :: POSIX
Classifier: Programming Language :: Python :: 3
Classifier: Programming Language :: Python :: 3.9
Classifier: Programming Language :: Python :: 3.10
Classifier: Programming Language :: Python :: 3.11
Classifier: Programming Language :: Python :: 3.12
Classifier: Programming Language :: Python :: 3.13
Requires-Python: >=3.9,<4
License-File: LICENSE
Requires-Dist: click<9,>=8.1.7
Requires-Dist: eip712<0.4,>=0.3
Requires-Dist: eth-ape<0.9,>=0.8.43
Requires-Dist: eth-utils<6,>=2.1.0
Requires-Dist: pydantic<3,>=2.10.2
Requires-Dist: requests<3,>=2.31.0
Requires-Dist: requests-ratelimiter<1,>=0.7
Provides-Extra: test
Requires-Dist: pytest>=6.0; extra == "test"
Requires-Dist: pytest-xdist; extra == "test"
Requires-Dist: pytest-cov; extra == "test"
Requires-Dist: hypothesis<7.0,>=6.2.0; extra == "test"
Requires-Dist: ape-foundry>=0.8.7; extra == "test"
Requires-Dist: ape-solidity>=0.8; extra == "test"
Provides-Extra: lint
Requires-Dist: mypy<2,>=1.13.0; extra == "lint"
Requires-Dist: types-requests; extra == "lint"
Requires-Dist: types-setuptools; extra == "lint"
Requires-Dist: ruff>=0.12.0; extra == "lint"
Requires-Dist: mdformat>=0.7.19; extra == "lint"
Requires-Dist: mdformat-gfm>=0.3.5; extra == "lint"
Requires-Dist: mdformat-frontmatter>=0.4.1; extra == "lint"
Requires-Dist: mdformat-pyproject>=0.0.2; extra == "lint"
Provides-Extra: docs
Requires-Dist: sphinx-ape<1,>=0.1; extra == "docs"
Provides-Extra: release
Requires-Dist: setuptools>=75.6.0; extra == "release"
Requires-Dist: wheel; extra == "release"
Requires-Dist: twine==3.8.0; extra == "release"
Provides-Extra: dev
Requires-Dist: pytest>=6.0; extra == "dev"
Requires-Dist: pytest-xdist; extra == "dev"
Requires-Dist: pytest-cov; extra == "dev"
Requires-Dist: hypothesis<7.0,>=6.2.0; extra == "dev"
Requires-Dist: ape-foundry>=0.8.7; extra == "dev"
Requires-Dist: ape-solidity>=0.8; extra == "dev"
Requires-Dist: mypy<2,>=1.13.0; extra == "dev"
Requires-Dist: types-requests; extra == "dev"
Requires-Dist: types-setuptools; extra == "dev"
Requires-Dist: ruff>=0.12.0; extra == "dev"
Requires-Dist: mdformat>=0.7.19; extra == "dev"
Requires-Dist: mdformat-gfm>=0.3.5; extra == "dev"
Requires-Dist: mdformat-frontmatter>=0.4.1; extra == "dev"
Requires-Dist: mdformat-pyproject>=0.0.2; extra == "dev"
Requires-Dist: sphinx-ape<1,>=0.1; extra == "dev"
Requires-Dist: setuptools>=75.6.0; extra == "dev"
Requires-Dist: wheel; extra == "dev"
Requires-Dist: twine==3.8.0; extra == "dev"
Requires-Dist: commitizen; extra == "dev"
Requires-Dist: pre-commit; extra == "dev"
Requires-Dist: pytest-watch; extra == "dev"
Requires-Dist: IPython; extra == "dev"
Requires-Dist: ipdb; extra == "dev"
Dynamic: author
Dynamic: author-email
Dynamic: classifier
Dynamic: description
Dynamic: description-content-type
Dynamic: home-page
Dynamic: keywords
Dynamic: license
Dynamic: license-file
Dynamic: provides-extra
Dynamic: requires-dist
Dynamic: requires-python
Dynamic: summary
